multi_parser/__init__.py
multi_parser/__init__.pyi
multi_parser-23.12.2.dist-info/METADATA
multi_parser-23.12.2.dist-info/WHEEL
multi_parser-23.12.2.dist-info/RECORD
